LICENSE
MANIFEST.in
README.md
VERSION
setup.py
hubspot/__init__.py
hubspot/api_client.py
hubspot/client.py
hubspot/exceptions.py
hubspot/hubspot.py
hubspot/rest.py
hubspot/automation/__init__.py
hubspot/automation/actions/__init__.py
hubspot/automation/actions/api_client.py
hubspot/automation/actions/configuration.py
hubspot/automation/actions/exceptions.py
hubspot/automation/actions/rest.py
hubspot/automation/actions/api/__init__.py
hubspot/automation/actions/api/callbacks_api.py
hubspot/automation/actions/api/definitions_api.py
hubspot/automation/actions/api/functions_api.py
hubspot/automation/actions/api/revisions_api.py
hubspot/automation/actions/models/__init__.py
hubspot/automation/actions/models/batch_input_callback_completion_batch_request.py
hubspot/automation/actions/models/callback_completion_batch_request.py
hubspot/automation/actions/models/callback_completion_request.py
hubspot/automation/actions/models/collection_response_public_action_definition_forward_paging.py
hubspot/automation/actions/models/collection_response_public_action_function_identifier_no_paging.py
hubspot/automation/actions/models/collection_response_public_action_revision_forward_paging.py
hubspot/automation/actions/models/error.py
hubspot/automation/actions/models/error_detail.py
hubspot/automation/actions/models/field_type_definition.py
hubspot/automation/actions/models/forward_paging.py
hubspot/automation/actions/models/input_field_definition.py
hubspot/automation/actions/models/next_page.py
hubspot/automation/actions/models/option.py
hubspot/automation/actions/models/output_field_definition.py
hubspot/automation/actions/models/public_action_definition.py
hubspot/automation/actions/models/public_action_definition_egg.py
hubspot/automation/actions/models/public_action_definition_input_field_dependencies_inner.py
hubspot/automation/actions/models/public_action_definition_patch.py
hubspot/automation/actions/models/public_action_function.py
hubspot_api_client_async.egg-info/PKG-INFO
hubspot_api_client_async.egg-info/SOURCES.txt
hubspot_api_client_async.egg-info/dependency_links.txt
hubspot_api_client_async.egg-info/requires.txt
hubspot_api_client_async.egg-info/top_level.txt